{"chunk_definitions":[{"chunk_id":"c0cr4ckqhhygh","chunk_label":"unnamed-chunk-1","document_id":"E12B7F8","expansion_state":0,"options":{"engine":"r","label":"unnamed-chunk-1"},"row":7,"row_count":1,"visible":true},{"chunk_id":"c7oklmjittchx","chunk_label":"unnamed-chunk-2","document_id":"E12B7F8","expansion_state":0,"options":{"engine":"r","label":"unnamed-chunk-2"},"row":12,"row_count":1,"visible":true},{"chunk_id":"cmltzvaylwzrf","chunk_label":"unnamed-chunk-3","document_id":"E12B7F8","expansion_state":0,"options":{"engine":"r","label":"unnamed-chunk-6"},"row":18,"row_count":1,"visible":true},{"chunk_id":"cnnig0wrz99nu","chunk_label":"unnamed-chunk-4","document_id":"E12B7F8","expansion_state":0,"options":{"engine":"r","label":"unnamed-chunk-4"},"row":24,"row_count":1,"visible":true},{"chunk_id":"cz4r8kl5cgxnj","chunk_label":"unnamed-chunk-5","document_id":"E12B7F8","expansion_state":0,"options":{"engine":"r","label":"unnamed-chunk-5"},"row":30,"row_count":1,"visible":true},{"chunk_id":"cgi98ah9ftk92","chunk_label":"unnamed-chunk-6","document_id":"E12B7F8","expansion_state":0,"options":{"engine":"r","label":"unnamed-chunk-7"},"row":42,"row_count":1,"visible":true},{"chunk_id":"cyzjap5z9pvl9","chunk_label":"unnamed-chunk-7","document_id":"E12B7F8","expansion_state":0,"options":{"engine":"r","label":"unnamed-chunk-8"},"row":53,"row_count":1,"visible":true},{"chunk_id":"cmx2wnhgb4wve","chunk_label":"unnamed-chunk-8","document_id":"E12B7F8","expansion_state":0,"options":{"engine":"r","label":"unnamed-chunk-9"},"row":67,"row_count":1,"visible":true},{"chunk_id":"cv8w4x19ceohf","chunk_label":"unnamed-chunk-9","document_id":"87F1942E","expansion_state":0,"options":{"engine":"r","label":"unnamed-chunk-10"},"row":74,"row_count":1,"visible":true},{"chunk_id":"cu5880nzloh60","chunk_label":"unnamed-chunk-10","document_id":"87F1942E","expansion_state":0,"options":{"engine":"r","label":"unnamed-chunk-11"},"row":79,"row_count":1,"visible":true},{"chunk_id":"cbzndk48synaz","chunk_label":"unnamed-chunk-11","document_id":"BD23565A","expansion_state":0,"options":{"engine":"r","label":"unnamed-chunk-12"},"row":190,"row_count":1,"visible":true},{"chunk_id":"ckloej1g15djf","chunk_label":"unnamed-chunk-12","document_id":"BD23565A","expansion_state":0,"options":{"engine":"r","label":"unnamed-chunk-13"},"row":194,"row_count":1,"visible":true},{"chunk_id":"c6hml0drwk5go","chunk_label":"unnamed-chunk-13","document_id":"BD23565A","expansion_state":0,"options":{"engine":"r","label":"unnamed-chunk-14"},"row":240,"row_count":1,"visible":true},{"chunk_id":"ct1x1mt6usskp","chunk_label":"unnamed-chunk-14","document_id":"BD23565A","expansion_state":0,"options":{"engine":"r","label":"unnamed-chunk-15"},"row":244,"row_count":1,"visible":true},{"chunk_id":"cwrju80w0tgr2","chunk_label":"unnamed-chunk-15","document_id":"BD23565A","expansion_state":0,"options":{"engine":"r","label":"unnamed-chunk-16"},"row":250,"row_count":1,"visible":true},{"chunk_id":"chobowd51ofvc","chunk_label":"unnamed-chunk-16","document_id":"BD23565A","expansion_state":0,"options":{"engine":"r","label":"unnamed-chunk-20"},"row":261,"row_count":1,"visible":true},{"chunk_id":"cyx9t6ihdk9y6","chunk_label":"unnamed-chunk-17","document_id":"BD23565A","expansion_state":0,"options":{"engine":"r","label":"unnamed-chunk-21"},"row":269,"row_count":1,"visible":true},{"chunk_id":"c138m6370m6sw","chunk_label":"unnamed-chunk-18","document_id":"BD23565A","expansion_state":0,"options":{"engine":"r","label":"unnamed-chunk-22"},"row":277,"row_count":1,"visible":true},{"chunk_id":"cjyh697gkqags","chunk_label":"unnamed-chunk-19","document_id":"BD23565A","expansion_state":0,"options":{"engine":"r","label":"unnamed-chunk-23"},"row":282,"row_count":1,"visible":true},{"chunk_id":"cp8e35ty4wro4","chunk_label":"unnamed-chunk-20","document_id":"BD23565A","expansion_state":0,"options":{"engine":"r","label":"unnamed-chunk-24"},"row":298,"row_count":1,"visible":true},{"chunk_id":"cd14vuqpsdy4b","chunk_label":"unnamed-chunk-21","document_id":"BD23565A","expansion_state":0,"options":{"engine":"r","label":"unnamed-chunk-25"},"row":304,"row_count":1,"visible":true},{"chunk_id":"cdrhb7taxgq2a","chunk_label":"unnamed-chunk-22","document_id":"BD23565A","expansion_state":0,"options":{"engine":"r","label":"unnamed-chunk-26"},"row":311,"row_count":1,"visible":true},{"chunk_id":"cgt0nhkgwu5jm","chunk_label":"unnamed-chunk-23","document_id":"BD23565A","expansion_state":0,"options":{"engine":"r","label":"unnamed-chunk-27"},"row":318,"row_count":1,"visible":true},{"chunk_id":"cfkirhn8z12x0","chunk_label":"unnamed-chunk-24","document_id":"BD23565A","expansion_state":0,"options":{"engine":"r","label":"unnamed-chunk-28"},"row":323,"row_count":1,"visible":true},{"chunk_id":"c0o1ownmatygo","chunk_label":"unnamed-chunk-25","document_id":"BD23565A","expansion_state":0,"options":{"engine":"r","label":"unnamed-chunk-29"},"row":328,"row_count":1,"visible":true},{"chunk_id":"c3ukeo9ysq9qn","chunk_label":"unnamed-chunk-26","document_id":"BD23565A","expansion_state":0,"options":{"engine":"r","label":"unnamed-chunk-30"},"row":337,"row_count":1,"visible":true},{"chunk_id":"clghhuacvjzdn","chunk_label":"unnamed-chunk-27","document_id":"BD23565A","expansion_state":0,"options":{"engine":"r","label":"unnamed-chunk-31"},"row":344,"row_count":1,"visible":true},{"chunk_id":"c03suq26fdfe0","chunk_label":"unnamed-chunk-28","document_id":"BD23565A","expansion_state":0,"options":{"engine":"r","label":"unnamed-chunk-32"},"row":351,"row_count":1,"visible":true},{"chunk_id":"ck42grcv9eo1a","chunk_label":"unnamed-chunk-29","document_id":"BD23565A","expansion_state":0,"options":{"engine":"r","label":"unnamed-chunk-33"},"row":361,"row_count":1,"visible":true},{"chunk_id":"cuyotvepwb6b6","chunk_label":"unnamed-chunk-30","document_id":"BD23565A","expansion_state":0,"options":{"engine":"r","label":"unnamed-chunk-34"},"row":370,"row_count":1,"visible":true},{"chunk_id":"c1dbiqa1m0lt3","chunk_label":"unnamed-chunk-31","document_id":"BD23565A","expansion_state":0,"options":{"engine":"r","label":"unnamed-chunk-35"},"row":377,"row_count":1,"visible":true},{"chunk_id":"cd989k2asgcjr","chunk_label":"unnamed-chunk-32","document_id":"BD23565A","expansion_state":0,"options":{"engine":"r","label":"unnamed-chunk-145"},"row":382,"row_count":1,"visible":true},{"chunk_id":"cog30wkasinqq","chunk_label":"unnamed-chunk-32","document_id":"6B7E1F9","expansion_state":0,"options":{"engine":"r","label":"unnamed-chunk-36"},"row":383,"row_count":1,"visible":true},{"chunk_id":"c0vw7q0n8mbur","chunk_label":"unnamed-chunk-33","document_id":"6B7E1F9","expansion_state":0,"options":{"engine":"r","label":"unnamed-chunk-37"},"row":414,"row_count":1,"visible":true},{"chunk_id":"cwcvbumrbavb6","chunk_label":"unnamed-chunk-34","document_id":"6B7E1F9","expansion_state":0,"options":{"engine":"r","label":"unnamed-chunk-38"},"row":420,"row_count":1,"visible":true},{"chunk_id":"cfub68dttv1a6","chunk_label":"unnamed-chunk-35","document_id":"6B7E1F9","expansion_state":0,"options":{"engine":"r","label":"unnamed-chunk-39"},"row":427,"row_count":1,"visible":true},{"chunk_id":"cgq0gas4fy50r","chunk_label":"unnamed-chunk-36","document_id":"6B7E1F9","expansion_state":0,"options":{"engine":"r","label":"unnamed-chunk-40"},"row":432,"row_count":1,"visible":true}],"chunk_rendered_width":700,"doc_write_time":1573762837}